trame/__init__.py
trame/modules/__init__.py
trame/modules/markdown.py
trame/widgets/__init__.py
trame/widgets/markdown.py
trame_markdown/LICENSE
trame_markdown/__init__.py
trame_markdown/module/__init__.py
trame_markdown/module/serve/style.css
trame_markdown/module/serve/trame-markdown.umd.js
trame_markdown/module/serve/css/dark.css
trame_markdown/module/serve/css/light.css
trame_markdown/module/serve/dist/onig.wasm
trame_markdown/module/serve/languages/abap.tmLanguage.json
trame_markdown/module/serve/languages/actionscript-3.tmLanguage.json
trame_markdown/module/serve/languages/ada.tmLanguage.json
trame_markdown/module/serve/languages/apache.tmLanguage.json
trame_markdown/module/serve/languages/apex.tmLanguage.json
trame_markdown/module/serve/languages/apl.tmLanguage.json
trame_markdown/module/serve/languages/applescript.tmLanguage.json
trame_markdown/module/serve/languages/ara.tmLanguage.json
trame_markdown/module/serve/languages/asm.tmLanguage.json
trame_markdown/module/serve/languages/astro.tmLanguage.json
trame_markdown/module/serve/languages/awk.tmLanguage.json
trame_markdown/module/serve/languages/ballerina.tmLanguage.json
trame_markdown/module/serve/languages/bat.tmLanguage.json
trame_markdown/module/serve/languages/beancount.tmLanguage.json
trame_markdown/module/serve/languages/berry.tmLanguage.json
trame_markdown/module/serve/languages/bibtex.tmLanguage.json
trame_markdown/module/serve/languages/bicep.tmLanguage.json
trame_markdown/module/serve/languages/blade.tmLanguage.json
trame_markdown/module/serve/languages/c.tmLanguage.json
trame_markdown/module/serve/languages/cadence.tmLanguage.json
trame_markdown/module/serve/languages/clarity.tmLanguage.json
trame_markdown/module/serve/languages/clojure.tmLanguage.json
trame_markdown/module/serve/languages/cmake.tmLanguage.json
trame_markdown/module/serve/languages/cobol.tmLanguage.json
trame_markdown/module/serve/languages/codeql.tmLanguage.json
trame_markdown/module/serve/languages/coffee.tmLanguage.json
trame_markdown-3.1.0.dist-info/LICENSE
trame_markdown-3.1.0.dist-info/METADATA
trame_markdown-3.1.0.dist-info/WHEEL
trame_markdown-3.1.0.dist-info/top_level.txt
trame_markdown-3.1.0.dist-info/RECORD
